main.py
mcp_weacher_server-0.1.0.dist-info/METADATA
mcp_weacher_server-0.1.0.dist-info/WHEEL
mcp_weacher_server-0.1.0.dist-info/entry_points.txt
mcp_weacher_server-0.1.0.dist-info/top_level.txt
mcp_weacher_server-0.1.0.dist-info/RECORD
